eggplant/__main__.py
eggplant-0.1.0.dist-info/WHEEL
eggplant-0.1.0.dist-info/METADATA
eggplant-0.1.0.dist-info/RECORD
