Metadata-Version: 2.1
Name: eggplant
Version: 0.1.0
Summary: 
License: AGPL-3.0-or-later
Author: Stefano Pigozzi
Author-email: me@steffo.eu
Requires-Python: >=3.9,<4.0
Classifier: License :: OSI Approved :: GNU Affero General Public License v3 or later (AGPLv3+)
Classifier: Programming Language :: Python :: 3
Requires-Dist: fastapi (>=0.63.0,<0.64.0)
Requires-Dist: psycopg2 (>=2.8.6,<3.0.0)
Requires-Dist: royalnet (>=6.0.2,<7.0.0)
Requires-Dist: sqlalchemy (>=1.3.22,<2.0.0)
Requires-Dist: uvicorn (>=0.13.3,<0.14.0)
